subgraph/simplegraph/__init__.py
subgraph/simplegraph/simplegraph.py
subgraph-0.0.1.dist-info/LICENSE
subgraph-0.0.1.dist-info/METADATA
subgraph-0.0.1.dist-info/WHEEL
subgraph-0.0.1.dist-info/top_level.txt
subgraph-0.0.1.dist-info/RECORD
