Metadata-Version: 2.1
Name: subgraph
Version: 0.0.1
Summary: A subgraph library
Author-email: Lucas Jones <lucasjonesdev@hotmail.co.uk>
Classifier: Programming Language :: Python :: 3
Classifier: License :: OSI Approved :: MIT License
Classifier: Operating System :: OS Independent
License-File: LICENSE
